positron_cross_section/__init__.py
positron_cross_section/gas.py
positron_cross_section/gtcs.py
positron_cross_section/main.py
positron_cross_section/plot.py
positron_cross_section-0.0.42.dist-info/LICENSE
positron_cross_section-0.0.42.dist-info/METADATA
positron_cross_section-0.0.42.dist-info/WHEEL
positron_cross_section-0.0.42.dist-info/entry_points.txt
positron_cross_section-0.0.42.dist-info/top_level.txt
positron_cross_section-0.0.42.dist-info/RECORD
