Metadata-Version: 2.1
Name: positron-cross-section
Version: 0.0.42
Summary: "A program for calculating and plotting positron cross sections."
Home-page: https://github.com/ryanstocks00/positron-cross-section
Author: Ryan Stocks
Author-email: ryan.stocks@anu.edu.au
License: MIT
Platform: UNKNOWN
Requires-Python: >=3.7
License-File: LICENSE
Requires-Dist: typer
Requires-Dist: pytest
Requires-Dist: pandas
Requires-Dist: pandas-stubs
Requires-Dist: numpy
Requires-Dist: matplotlib
Requires-Dist: pydantic
Requires-Dist: uncertainties
